thunderlight/__init__.py
thunderlight/app.py
thunderlight/asgi.py
thunderlight/ctx.py
thunderlight/formparsers.py
thunderlight/handler.py
thunderlight/json.py
thunderlight/matcher.py
thunderlight/middleware.py
thunderlight/next.py
thunderlight/py.typed
thunderlight/req.py
thunderlight/res.py
thunderlight/state.py
thunderlight-0.6.0.dist-info/METADATA
thunderlight-0.6.0.dist-info/WHEEL
thunderlight-0.6.0.dist-info/top_level.txt
thunderlight-0.6.0.dist-info/RECORD
