Metadata-Version: 2.1
Name: thunderlight
Version: 0.6.0
Summary: A Python HTTP Server.
Home-page: https://github.com/fillmula/thunderlight
Author: Victor Teo
Author-email: victor.teo@fillmula.com
License: MIT
Platform: UNKNOWN
Classifier: Programming Language :: Python :: 3.10
Requires-Python: >=3.10
Requires-Dist: python-multipart (==0.0.5)
Requires-Dist: uvicorn (<0.18.0,>=0.17.6)
Requires-Dist: anyio (<4.0.0,>=3.5.0)
